pastas_plugins/__init__.py
pastas_plugins/version.py
pastas_plugins/cross_correlation/__init__.py
pastas_plugins/cross_correlation/cross_correlation.py
pastas_plugins/cross_correlation/plots.py
pastas_plugins/cross_correlation/version.py
pastas_plugins/modflow/__init__.py
pastas_plugins/modflow/modflow.py
pastas_plugins/modflow/stressmodels.py
pastas_plugins/modflow/version.py
pastas_plugins/pest/__init__.py
pastas_plugins/pest/solver.py
pastas_plugins/pest/version.py
pastas_plugins/reservoirs/__init__.py
pastas_plugins/reservoirs/reservoir.py
pastas_plugins/reservoirs/stressmodels.py
pastas_plugins/reservoirs/version.py
pastas_plugins/responses/__init__.py
pastas_plugins/responses/parameters.py
pastas_plugins/responses/rfunc.py
pastas_plugins/responses/version.py
pastas_plugins-0.3.4.dist-info/licenses/LICENSE
pastas_plugins-0.3.4.dist-info/METADATA
pastas_plugins-0.3.4.dist-info/WHEEL
pastas_plugins-0.3.4.dist-info/top_level.txt
pastas_plugins-0.3.4.dist-info/RECORD
