Metadata-Version: 2.4
Name: pastas_plugins
Version: 0.3.4
Summary: Repository containing plugins to further enhance your pastas experience.
Author: Pastas Developers Team
Maintainer-email: "D.A. Brakenhoff" <d.brakenhoff@artesia-water.nl>, "M.A. Vonk" <m.vonk@artesia-water.nl>, "M. Bakker" <markbak@gmail.com>
License: MIT License
Project-URL: homepage, https://pastas.dev
Project-URL: repository, https://github.com/pastas/pastas-plugins
Project-URL: documentation, https://pastas.readthedocs.io
Keywords: hydrology,groundwater,timeseries,analysis
Classifier: Development Status :: 3 - Alpha
Classifier: Intended Audience :: Science/Research
Classifier: Intended Audience :: Other Audience
Classifier: License :: OSI Approved :: MIT License
Classifier: Programming Language :: Python :: 3 :: Only
Classifier: Programming Language :: Python :: 3.10
Classifier: Programming Language :: Python :: 3.11
Classifier: Programming Language :: Python :: 3.12
Classifier: Programming Language :: Python :: 3.13
Classifier: Topic :: Scientific/Engineering :: Hydrology
Requires-Python: >=3.10
License-File: LICENSE
Requires-Dist: pastas
Provides-Extra: all
Requires-Dist: pastas_plugins[crosscorrelation,modflow,pest]; extra == "all"
Provides-Extra: crosscorrelation
Requires-Dist: statsmodels; extra == "crosscorrelation"
Provides-Extra: modflow
Requires-Dist: flopy; extra == "modflow"
Provides-Extra: pest
Requires-Dist: pyemu>=1.3.8; extra == "pest"
Requires-Dist: tqdm; extra == "pest"
Provides-Extra: reservoirs
Requires-Dist: pastas_plugins; extra == "reservoirs"
Provides-Extra: responses
Requires-Dist: pastas_plugins; extra == "responses"
Provides-Extra: ruffing
Requires-Dist: ruff; extra == "ruffing"
Provides-Extra: pytesting
Requires-Dist: pytest>=7; extra == "pytesting"
Requires-Dist: pytest-cov; extra == "pytesting"
Requires-Dist: pytest-sugar; extra == "pytesting"
Provides-Extra: ci
Requires-Dist: coverage; extra == "ci"
Provides-Extra: rtd
Requires-Dist: pastas_plugins[all]; extra == "rtd"
Requires-Dist: sphinx_rtd_theme; extra == "rtd"
Requires-Dist: myst_nb; extra == "rtd"
Requires-Dist: numpydoc; extra == "rtd"
Requires-Dist: sphinx_design; extra == "rtd"
Requires-Dist: tqdm; extra == "rtd"
Requires-Dist: xarray; extra == "rtd"
Requires-Dist: cmcrameri; extra == "rtd"
Dynamic: license-file
